vm.v
module vm(
    input [1:0] coin_in,
    input beverage_take,
    input change_take,
    input clk,
    input rstn,
    output reg [4:0] money_account,
    output reg beverage_out,
    output reg [1:0] change_out
);

reg [4:0] c_state;
reg [4:0] n_state;
reg c_beverage_state, n_beverage_state;
reg c_change_state, n_change_state;
reg [4:0] temp_c_state;

localparam not_take = 1'b0;
localparam take = 1'b1;

localparam [4:0] S0 = 5'b00000;
localparam [4:0] S1 = 5'b00001;
localparam [4:0] S2 = 5'b00010;
localparam [4:0] S3 = 5'b00011;
localparam [4:0] S4 = 5'b00100;
localparam [4:0] S5 = 5'b00101;
localparam [4:0] S6 = 5'b00110;
localparam [4:0] S7 = 5'b00111;
localparam [4:0] S8 = 5'b01000;
localparam [4:0] S9 = 5'b01001;
localparam [4:0] S10 = 5'b01010;
localparam [4:0] S11 = 5'b01011;
localparam [4:0] S12 = 5'b01100;
localparam [4:0] S13 = 5'b01101;
localparam [4:0] S14 = 5'b01110;
localparam [4:0] S15 = 5'b01111;
localparam [4:0] S16 = 5'b10000;
localparam [4:0] S17 = 5'b10001;
localparam [4:0] S18 = 5'b10010;
localparam [4:0] S19 = 5'b10011;
localparam [4:0] S20 = 5'b10100;
localparam [4:0] S21 = 5'b10101;
localparam [4:0] S22 = 5'b10110;
localparam [4:0] S23 = 5'b10111;
localparam [4:0] S24 = 5'b11000;
localparam [4:0] S25 = 5'b11001;

always@(posedge clk or negedge rstn) begin
    if(!rstn) begin
        c_state = S0;
        c_beverage_state = not_take;
        c_change_state = not_take;
        temp_c_state = S0;
    end else begin
        temp_c_state = c_state;
        c_state = n_state;
        c_beverage_state = n_beverage_state;
        c_change_state = n_change_state;
    end
end

always@(*) begin
    n_beverage_state = c_beverage_state;

    if(coin_in == 2'b01 && beverage_take == 1'b1 || coin_in == 2'b10 && beverage_take == 1'b1 || 
            coin_in == 2'b01 && change_take == 1'b1 || coin_in == 2'b10 && change_take == 1'b1 ||
            beverage_take == 1'b1 && change_take == 1'b1) begin n_beverage_state = not_take; end
    else if(beverage_take == 1'b0) begin n_beverage_state = not_take; end
    else if(beverage_take == 1'b1) begin n_beverage_state = take; end
end

always@(*) begin
    n_state = c_state;
    if(coin_in == 2'b01 && beverage_take == 1'b1 || coin_in == 2'b10 && beverage_take == 1'b1 || 
        coin_in == 2'b01 && change_take == 1'b1 || coin_in == 2'b10 && change_take == 1'b1 || 
        beverage_take == 1'b1 && change_take == 1'b1) begin n_state = n_state; end
    else begin
        case(n_state) 
            S0: begin
                if(change_take == 1'b1 || c_change_state == take) n_state = S0;
                else if(beverage_take == 1'b1) n_state = S0;
                else if(coin_in == 2'b10) n_state = S5; 
                else if(coin_in == 2'b01) n_state = S1; 
            end
            S1: begin
                if(change_take == 1'b1 || c_change_state == take) n_state = S0;
                else if(beverage_take == 1'b1) n_state = S1; 
                else if(coin_in == 2'b10) n_state = S6; 
                else if(coin_in == 2'b01) n_state = S2; 
            end
            S2: begin
                if(change_take == 1'b1 || c_change_state == take) n_state = S1;
                else if(beverage_take == 1'b1) n_state = S2; 
                else if(coin_in == 2'b10) n_state = S7; 
                else if(coin_in == 2'b01) n_state = S3; 
            end
            S3: begin
                if(change_take == 1'b1 || c_change_state == take) n_state = S2;
                else if(beverage_take == 1'b1) n_state = S3; 
                else if(coin_in == 2'b10) n_state = S8; 
                else if(coin_in == 2'b01) n_state = S4; 
            end
            S4: begin
                if(change_take == 1'b1 || c_change_state == take) n_state = S3;
                else if(beverage_take == 1'b1) n_state = S4; 
                else if(coin_in == 2'b10) n_state = S9; 
                else if(coin_in == 2'b01) n_state = S5; 
            end
            S5: begin 
                if(change_take == 1'b1 || c_change_state == take) n_state = S0;
                else if(beverage_take == 1'b1) n_state = S5; 
                else if(coin_in == 2'b10) n_state = S10; 
                else if(coin_in == 2'b01) n_state = S6; 
            end
            S6: begin
                if(change_take == 1'b1 || c_change_state == take) n_state = S1;
                else if(beverage_take == 1'b1) n_state = S6; 
                else if(coin_in == 2'b10) n_state = S11; 
                else if(coin_in == 2'b01) n_state = S7; 
            end
            S7: begin
                if(change_take == 1'b1 || c_change_state == take) n_state = S2;
                else if(beverage_take == 1'b1) n_state = S7; 
                else if(coin_in == 2'b10) n_state = S12; 
                else if(coin_in == 2'b01) n_state = S8; 
            end
            S8: begin
                if(change_take == 1'b1 || c_change_state == take) n_state = S3;
                else if(beverage_take == 1'b1) n_state = S8;
                else if(coin_in == 2'b10) n_state = S13; 
                else if(coin_in == 2'b01) n_state = S9; 
            end
            S9: begin
                if(change_take == 1'b1 || c_change_state == take) n_state = S4;
                else if(beverage_take == 1'b1) n_state = S9; 
                else if(coin_in == 2'b10) n_state = S14; 
                else if(coin_in == 2'b01) n_state = S10; 
            end
            S10: begin
                if(change_take == 1'b1 || c_change_state == take) n_state = S5;
                else if(beverage_take == 1'b1) n_state = S0; 
                else if(coin_in == 2'b10) n_state = S15; 
                else if(coin_in == 2'b01) n_state = S11; 
            end
            S11: begin
                if(change_take == 1'b1 || c_change_state == take) n_state = S6;
                else if(beverage_take == 1'b1) n_state = S1; 
                else if(coin_in == 2'b10) n_state = S16; 
                else if(coin_in == 2'b01) n_state = S12; 
            end
            S12: begin
                if(change_take == 1'b1 || c_change_state == take) n_state = S7;
                else if(beverage_take == 1'b1) n_state = S2; 
                else if(coin_in == 2'b10) n_state = S17; 
                else if(coin_in == 2'b01) n_state = S13; 
            end
            S13: begin
                if(change_take == 1'b1 || c_change_state == take) n_state = S8;
                else if(beverage_take == 1'b1) n_state = S3; 
                else if(coin_in == 2'b10) n_state = S18; 
                else if(coin_in == 2'b01) n_state = S14; 
            end
            S14: begin
                if(change_take == 1'b1 || c_change_state == take) n_state = S9;
                else if(beverage_take == 1'b1) n_state = S4; 
                else if(coin_in == 2'b10) n_state = S19; 
                else if(coin_in == 2'b01) n_state = S15; 
            end
            S15: begin
                if(change_take == 1'b1 || c_change_state == take) n_state = S10;
                else if(beverage_take == 1'b1) n_state = S5; 
                else if(coin_in == 2'b10) n_state = S20; 
                else if(coin_in == 2'b01) n_state = S16; 
            end
            S16: begin
                if(change_take == 1'b1 || c_change_state == take) n_state = S11;
                else if(beverage_take == 1'b1) n_state = S6; 
                else if(coin_in == 2'b10) n_state = S21; 
                else if(coin_in == 2'b01) n_state = S17; 
            end
            S17: begin
                if(change_take == 1'b1 || c_change_state == take) n_state = S12;
                else if(beverage_take == 1'b1) n_state = S7; 
                else if(coin_in == 2'b10) n_state = S22; 
                else if(coin_in == 2'b01) n_state = S18; 
            end
            S18: begin
                if(change_take == 1'b1 || c_change_state == take) n_state = S13;
                else if(beverage_take == 1'b1) n_state = S8;
                else if(coin_in == 2'b10) n_state = S23; 
                else if(coin_in == 2'b01) n_state = S19; 
            end
            S19: begin
                if(change_take == 1'b1 || c_change_state == take) n_state = S14;
                else if(beverage_take == 1'b1) n_state = S9; 
                else if(coin_in == 2'b10) n_state = S24;
                else if(coin_in == 2'b01) n_state = S20;
            end
            S20: begin
                if(change_take == 1'b1 || c_change_state == take) n_state = S15; 
                else if(beverage_take == 1'b1) n_state = S10;
                else if(coin_in == 2'b10) n_state = S25; 
                else if(coin_in == 2'b01) n_state = S21; 
            end
            S21, S22, S23, S24, S25: begin
                if(change_take == 1'b1 || c_change_state == take) n_state = S15; 
                else if(beverage_take == 1'b1) n_state = S10; 
                else if(coin_in == 2'b10) n_state = S25; 
                else if(coin_in == 2'b01) n_state = S21; 
                else n_state = S20;
            end
        endcase
    end
end

always@(*) begin
    n_change_state = c_change_state;

    if(coin_in == 2'b01 && beverage_take == 1'b1 || coin_in == 2'b10 && beverage_take == 1'b1 || 
        coin_in == 2'b01 && change_take == 1'b1 || coin_in == 2'b10 && change_take == 1'b1 || 
        beverage_take == 1'b1 && change_take == 1'b1) begin n_change_state = not_take; end
    else if(c_change_state == take && temp_c_state != S0) begin n_change_state = take; end
    else if(change_take == 1'b0) begin n_change_state = not_take; end 
    else if(change_take == 1'b1) begin n_change_state = take; end
end

always@(c_beverage_state or temp_c_state) begin
    case(c_beverage_state) 
        not_take:
            beverage_out = 1'b0;
        take: 
            case(temp_c_state)
                S0: beverage_out = 1'b0;
                S1: beverage_out = 1'b0;
                S2: beverage_out = 1'b0;
                S3: beverage_out = 1'b0;
                S4: beverage_out = 1'b0;
                S5: beverage_out = 1'b0;
                S6: beverage_out = 1'b0;
                S7: beverage_out = 1'b0;
                S8: beverage_out = 1'b0;
                S9: beverage_out = 1'b0;
                default : beverage_out = 1'b1;
            endcase
    endcase
end

always@(c_state) begin
    case(c_state)
    S0: begin money_account = 5'b00000; end
    S1: begin money_account = 5'b00001; end
    S2: begin money_account = 5'b00010; end
    S3: begin money_account = 5'b00011; end
    S4: begin money_account = 5'b00100; end
    S5: begin money_account = 5'b00101; end
    S6: begin money_account = 5'b00110; end
    S7: begin money_account = 5'b00111; end
    S8: begin money_account = 5'b01000; end
    S9: begin money_account = 5'b01001; end 
    S10: begin money_account = 5'b01010; end
    S11: begin money_account = 5'b01011; end
    S12: begin money_account = 5'b01100; end
    S13: begin money_account = 5'b01101; end
    S14: begin money_account = 5'b01110; end
    S15: begin money_account = 5'b01111; end
    S16: begin money_account = 5'b10000; end
    S17: begin money_account = 5'b10001; end
    S18: begin money_account = 5'b10010; end
    S19: begin money_account = 5'b10011; end
    S20: begin money_account = 5'b10100; end
    S21: begin money_account = 5'b10100; end
    S22: begin money_account = 5'b10100; end
    S23: begin money_account = 5'b10100; end
    S24: begin money_account = 5'b10100; end
    S25: begin money_account = 5'b10100; end
    endcase
end 

always@(c_change_state or temp_c_state or c_state) begin
    case(c_change_state)
    not_take:
        case(c_state) 
            S21: begin change_out = 2'b01; end
            S22: begin change_out = 2'b01; end
            S23: begin change_out = 2'b01; end
            S24: begin change_out = 2'b01; end
            S25: begin change_out = 2'b10; end
            default : change_out = 2'b00;
        endcase
    take:
        case(temp_c_state)
        S0: begin change_out = 2'b00; end
        S1: begin change_out = 2'b01; end
        S2: begin change_out = 2'b01; end
        S3: begin change_out = 2'b01; end
        S4: begin change_out = 2'b01; end
        S5: begin change_out = 2'b10; end
        S6: begin change_out = 2'b10; end
        S7: begin change_out = 2'b10; end
        S8: begin change_out = 2'b10; end
        S9: begin change_out = 2'b10; end 
        S10: begin change_out = 2'b10; end
        S11: begin change_out = 2'b10; end
        S12: begin change_out = 2'b10; end
        S13: begin change_out = 2'b10; end
        S14: begin change_out = 2'b10; end
        S15: begin change_out = 2'b10; end
        S16: begin change_out = 2'b10; end
        S17: begin change_out = 2'b10; end
        S18: begin change_out = 2'b10; end
        S19: begin change_out = 2'b10; end
        S20: begin change_out = 2'b10; end
        S21: begin change_out = 2'b10; end
        S22: begin change_out = 2'b10; end
        S23: begin change_out = 2'b10; end
        S24: begin change_out = 2'b10; end
        S25: begin change_out = 2'b10; end
        endcase
    endcase
end

endmodule

vm_tb.v
`timescale 1ns/1ns
module vm_tb;

reg [1:0]coin_in;
reg beverage_take;
reg change_take;
reg clk;
reg rstn;
wire [4:0] money_account;
wire beverage_out;
wire [1:0]change_out;

vm u_vm(
    .coin_in(coin_in),
    .beverage_take(beverage_take),
    .change_take(change_take),
    .clk(clk),
    .rstn(rstn),
    .money_account(money_account),
    .beverage_out(beverage_out),
    .change_out(change_out)
);

always 
    #5 clk = ~clk;

initial begin
    $dumpfile("vm.vcd");
    $dumpvars(0);
end

initial begin
    rstn = 1'b0; coin_in = 2'b00; clk = 1'b0; beverage_take = 1'b0; change_take = 1'b0;
    #10 rstn = 1;

    /*
        요구사항 1 : 여러 입력이 들어오는 경우 아무런 동작을 수행하지 않는다.

        1. 잔돈 반환과 동전 입력이 동시에 입력으로 들어온 경우
        2. 음료 호출과 잔돈 반환이 동시에 입력으로 들어온 경우
        3. 음료 호출과 동전 입력이 동시에 입력으로 들어온 경우
        4. 음료 호출과 잔돈 반환과 동전 입력이 모두 동시에 입력으로 들어온 경우
    */    
    @(posedge clk) coin_in = 2'b10; beverage_take = 1'b0; change_take = 1'b0;
    @(posedge clk) coin_in = 2'b10; beverage_take = 1'b0; change_take = 1'b0; 
    @(posedge clk) coin_in = 2'b01; beverage_take = 1'b0; change_take = 1'b1;
    @(posedge clk) coin_in = 2'b00; beverage_take = 1'b1; change_take = 1'b1;
    @(posedge clk) coin_in = 2'b01; beverage_take = 1'b1; change_take = 1'b0; 
    @(posedge clk) coin_in = 2'b01; beverage_take = 1'b1; change_take = 1'b1;

    @(posedge clk) coin_in = 2'b00; beverage_take = 1'b0; change_take = 1'b0;
    @(posedge clk) coin_in = 2'b00; beverage_take = 1'b0; change_take = 1'b0;
   

   /*
        요구사항 2 : 자판기에 20,000원을 초과해서 넣을 수 없다. 
                    만약 자판기에 20,000원을 초과하여 돈이 들어온다면 20,000원을 초과하여 오르지 않고 초과된 돈의 양만큼 잔돈으로 반환된다.
   */
   // 자판기에 21,000원이 들어온 경우
    @(posedge clk) coin_in = 2'b10; beverage_take = 1'b0; change_take = 1'b0;
    @(posedge clk) coin_in = 2'b10; beverage_take = 1'b0; change_take = 1'b0;
    @(posedge clk) coin_in = 2'b01; beverage_take = 1'b0; change_take = 1'b0;

    // 자판기에 25,000원이 들어온 경우
    @(posedge clk) coin_in = 2'b10; beverage_take = 1'b0; change_take = 1'b0;

    @(posedge clk) coin_in = 2'b00; beverage_take = 1'b0; change_take = 1'b0;
    @(posedge clk) coin_in = 2'b00; beverage_take = 1'b0; change_take = 1'b0;


    /*
        요구사항 3 : 자판기의 돈이 음료의 가격(10,000원)보다 적을 경우 뽑을 수 없다.
    */
    // 음료 호출 2번
    @(posedge clk) coin_in = 2'b00; beverage_take = 1'b1; change_take = 1'b0;
    @(posedge clk) coin_in = 2'b00; beverage_take = 1'b1; change_take = 1'b0;

    // 5,000원 동전 입력
    @(posedge clk) coin_in = 2'b10; beverage_take = 1'b0; change_take = 1'b0;
    // 자판기의 돈이 10,000원보다 적을 때 음료 호출
    @(posedge clk) coin_in = 2'b00; beverage_take = 1'b1; change_take = 1'b0;


    @(posedge clk) coin_in = 2'b00; beverage_take = 1'b0; change_take = 1'b0;
    @(posedge clk) coin_in = 2'b00; beverage_take = 1'b0; change_take = 1'b0;

    /*
        요구사항 4 : 잔돈을 반환할 때 5,000원이 반환이 가능하면 5,000원을 반환하고, 불가능하다면 1,000원을 반환한다.
    */
    // 자판기의 돈이 13,000원 일 때 음료 호출한 후 잔돈 반환 -> 3,000원이 반환되어야하므로 1,000원이 3번 반환
    @(posedge clk) coin_in = 2'b10; beverage_take = 1'b0; change_take = 1'b0;
    @(posedge clk) coin_in = 2'b01; beverage_take = 1'b0; change_take = 1'b0;
    @(posedge clk) coin_in = 2'b01; beverage_take = 1'b0; change_take = 1'b0;
    @(posedge clk) coin_in = 2'b01; beverage_take = 1'b0; change_take = 1'b0;
    @(posedge clk) coin_in = 2'b00; beverage_take = 1'b1; change_take = 1'b0;
    @(posedge clk) coin_in = 2'b00; beverage_take = 1'b0; change_take = 1'b1;
    @(posedge clk) coin_in = 2'b10; beverage_take = 1'b0; change_take = 1'b0;

    @(posedge clk) coin_in = 2'b00; beverage_take = 1'b0; change_take = 1'b0;
    @(posedge clk) coin_in = 2'b00; beverage_take = 1'b0; change_take = 1'b0;
    @(posedge clk) coin_in = 2'b00; beverage_take = 1'b0; change_take = 1'b0;

    // 자판기의 돈이 18,000원 일 때 음료 호출한 후 잔돈 반환 -> 8,000원이 반환되어야하므로 5,000원 한번과 1,000원이 3번 반환
    @(posedge clk) coin_in = 2'b10; beverage_take = 1'b0; change_take = 1'b0;
    @(posedge clk) coin_in = 2'b10; beverage_take = 1'b0; change_take = 1'b0;
    @(posedge clk) coin_in = 2'b10; beverage_take = 1'b0; change_take = 1'b0;
    @(posedge clk) coin_in = 2'b01; beverage_take = 1'b0; change_take = 1'b0;
    @(posedge clk) coin_in = 2'b01; beverage_take = 1'b0; change_take = 1'b0;
    @(posedge clk) coin_in = 2'b01; beverage_take = 1'b0; change_take = 1'b0;
    @(posedge clk) coin_in = 2'b00; beverage_take = 1'b1; change_take = 1'b0;
    @(posedge clk) coin_in = 2'b00; beverage_take = 1'b0; change_take = 1'b1;


    @(posedge clk) coin_in = 2'b00; beverage_take = 1'b0; change_take = 1'b0;
    @(posedge clk) coin_in = 2'b00; beverage_take = 1'b0; change_take = 1'b0;
    #50$finish;
end

endmodule

vm.vcd
$date
	Tue Nov 05 22:26:30 2024
$end
$version
	Icarus Verilog
$end
$timescale
	1ns
$end
$scope module vm_tb $end
$var wire 5 ! money_account [4:0] $end
$var wire 2 " change_out [1:0] $end
$var wire 1 # beverage_out $end
$var reg 1 $ beverage_take $end
$var reg 1 % change_take $end
$var reg 1 & clk $end
$var reg 2 ' coin_in [1:0] $end
$var reg 1 ( rstn $end
$scope module u_vm $end
$var wire 1 $ beverage_take $end
$var wire 1 % change_take $end
$var wire 1 & clk $end
$var wire 2 ) coin_in [1:0] $end
$var wire 1 ( rstn $end
$var reg 1 # beverage_out $end
$var reg 1 * c_beverage_state $end
$var reg 1 + c_change_state $end
$var reg 5 , c_state [4:0] $end
$var reg 2 - change_out [1:0] $end
$var reg 5 . money_account [4:0] $end
$var reg 1 / n_beverage_state $end
$var reg 1 0 n_change_state $end
$var reg 5 1 n_state [4:0] $end
$var reg 5 2 temp_c_state [4:0] $end
$upscope $end
$upscope $end
$enddefinitions $end
#0
$dumpvars
b0 2
b0 1
00
0/
b0 .
b0 -
b0 ,
0+
0*
b0 )
0(
b0 '
0&
0%
0$
0#
b0 "
b0 !
$end
#5
1&
#10
0&
1(
#15
b101 1
b10 '
b10 )
1&
#20
0&
#25
b101 !
b101 .
b1010 1
b101 ,
1&
#30
0&
#35
b1010 !
b1010 .
b1010 ,
b101 2
1%
b1 '
b1 )
1&
#40
0&
#45
b1010 2
1$
b0 '
b0 )
1&
#50
0&
#55
0%
b1 '
b1 )
1&
#60
0&
#65
1%
1&
#70
0&
#75
0%
0$
b0 '
b0 )
1&
#80
0&
#85
1&
#90
0&
#95
b1111 1
b10 '
b10 )
1&
#100
0&
#105
b1111 !
b1111 .
b10100 1
b1111 ,
1&
#110
0&
#115
b10100 !
b10100 .
b10101 1
b10100 ,
b1111 2
b1 '
b1 )
1&
#120
0&
#125
b1 "
b1 -
b11001 1
b10101 ,
b10100 2
b10 '
b10 )
1&
#130
0&
#135
b10 "
b10 -
b10100 1
b11001 ,
b10101 2
b0 '
b0 )
1&
#140
0&
#145
b0 "
b0 -
b10100 ,
b11001 2
1&
#150
0&
#155
b1010 1
1/
b10100 2
1$
1&
#160
0&
#165
1#
b1010 !
b1010 .
b0 1
1*
b1010 ,
1&
#170
0&
#175
b0 !
b0 .
b101 1
0/
b0 ,
b1010 2
0$
b10 '
b10 )
1&
#180
0&
#185
b101 !
b101 .
0#
1/
0*
b101 ,
b0 2
1$
b0 '
b0 )
1&
#190
0&
#195
0/
1*
b101 2
0$
1&
#200
0&
#205
0*
1&
#210
0&
#215
b1010 1
b10 '
b10 )
1&
#220
0&
#225
b1010 !
b1010 .
b1011 1
b1010 ,
b1 '
b1 )
1&
#230
0&
#235
b1011 !
b1011 .
b1100 1
b1011 ,
b1010 2
1&
#240
0&
#245
b1100 !
b1100 .
b1101 1
b1100 ,
b1011 2
1&
#250
0&
#255
b1101 !
b1101 .
b11 1
1/
b1101 ,
b1100 2
1$
b0 '
b0 )
1&
#260
0&
#265
b11 !
b11 .
1#
10
b10 1
0/
1*
b11 ,
b1101 2
1%
0$
1&
#270
0&
#275
b10 !
b10 .
b1 "
b1 -
0#
b1 1
1+
0*
b10 ,
b11 2
0%
b10 '
b10 )
1&
#280
0&
#285
b1 !
b1 .
b0 1
b1 ,
b10 2
b0 '
b0 )
1&
#290
0&
#295
b0 !
b0 .
b0 ,
b1 2
1&
#300
0&
#305
b0 "
b0 -
00
b0 2
1&
#310
0&
#315
b101 1
0+
b10 '
b10 )
1&
#320
0&
#325
b101 !
b101 .
b1010 1
b101 ,
1&
#330
0&
#335
b1010 !
b1010 .
b1111 1
b1010 ,
b101 2
1&
#340
0&
#345
b1111 !
b1111 .
b10000 1
b1111 ,
b1010 2
b1 '
b1 )
1&
#350
0&
#355
b10000 !
b10000 .
b10001 1
b10000 ,
b1111 2
1&
#360
0&
#365
b10001 !
b10001 .
b10010 1
b10001 ,
b10000 2
1&
#370
0&
#375
b10010 !
b10010 .
b1000 1
1/
b10010 ,
b10001 2
1$
b0 '
b0 )
1&
#380
0&
#385
b1000 !
b1000 .
1#
10
b11 1
0/
1*
b1000 ,
b10010 2
1%
0$
1&
#390
0&
#395
b11 !
b11 .
b10 "
b10 -
0#
b10 1
1+
0*
b11 ,
b1000 2
0%
1&
#400
0&
#405
b10 !
b10 .
b1 1
b1 "
b1 -
b10 ,
b11 2
1&
#410
0&
#415
b1 !
b1 .
b0 1
b1 ,
b10 2
1&
#420
0&
#425
b0 !
b0 .
b0 ,
b1 2
1&
#430
0&
#435
b0 "
b0 -
00
b0 2
1&
#440
0&
#445
0+
1&
